{
  "cefr": "A2",
  "level": 180,
  "tier": "basic",
  "words": [
    {
      "id": "A2-180-001",
      "level": 180,
      "tier": "basic",
      "cefr": "A2",
      "toeic_score_min": 200,
      "word": "matter",
      "pos": [
        "noun",
        "verb"
      ],
      "conjugations": {
        "plural": "matters",
        "present_3rd": "matters",
        "past": "mattered",
        "past_participle": "mattered",
        "ing": "mattering"
      },
      "domain": "general",
      "translations": [
        {
          "lang": "zh-TW",
          "lang_word": "matter",
          "definition": "n. 事情、事務、物質  v. 要緊、關係重大"
        }
      ],
      "examples": [
        {
          "en": "The board will discuss the matter at tomorrow's meeting.",
          "highlight": [
            "matter"
          ],
          "translations": {
            "zh-TW": "董事會將在明天的會議上討論這件事。"
          }
        },
        {
          "en": "It didn't matter how hard he tried; the deal fell through.",
          "highlight": [
            "matter"
          ],
          "translations": {
            "zh-TW": "不管他多麼努力，這筆交易還是破局了。"
          }
        },
        {
          "en": "Quality matters a great deal in this industry.",
          "highlight": [
            "matters"
          ],
          "translations": {
            "zh-TW": "在這個行業中，品質非常重要。"
          }
        }
      ],
      "synonyms": [
        "issue",
        "subject",
        "concern"
      ],
      "antonyms": [
        "triviality"
      ],
      "phrases": [
        "no matter",
        "matter of fact",
        "subject matter",
        "what's the matter"
      ]
    },
    {
      "id": "A2-180-002",
      "level": 180,
      "tier": "basic",
      "cefr": "A2",
      "toeic_score_min": 200,
      "word": "maximum",
      "pos": [
        "noun",
        "adjective"
      ],
      "conjugations": {
        "plural": "maximums"
      },
      "domain": "general",
      "translations": [
        {
          "lang": "zh-TW",
          "lang_word": "maximum",
          "definition": "n. 最大量、最高極限  adj. 最高的、最大的"
        }
      ],
      "examples": [
        {
          "en": "The maximum capacity of the venue is five hundred guests.",
          "highlight": [
            "maximum"
          ],
          "translations": {
            "zh-TW": "這個場地的最大容量是五百位賓客。"
          }
        },
        {
          "en": "The branches set their own maximums for the daily withdrawal.",
          "highlight": [
            "maximums"
          ],
          "translations": {
            "zh-TW": "各分行自行設定每日提款的最高限額。"
          }
        },
        {
          "en": "Drivers must obey the maximum speed limit on the highway.",
          "highlight": [
            "maximum"
          ],
          "translations": {
            "zh-TW": "駕駛人必須遵守高速公路上的最高速限。"
          }
        }
      ],
      "synonyms": [
        "peak",
        "greatest",
        "highest"
      ],
      "antonyms": [
        "minimum",
        "least"
      ],
      "phrases": [
        "maximum capacity",
        "maximum amount",
        "maximum limit",
        "reach the maximum"
      ]
    },
    {
      "id": "A2-180-003",
      "level": 180,
      "tier": "basic",
      "cefr": "A2",
      "toeic_score_min": 200,
      "word": "may",
      "pos": [
        "verb",
        "noun"
      ],
      "conjugations": {
        "plural": "Mays"
      },
      "domain": "general",
      "translations": [
        {
          "lang": "zh-TW",
          "lang_word": "may",
          "definition": "aux. 可以、也許  n. 五月"
        }
      ],
      "examples": [
        {
          "en": "May I see your membership card, please?",
          "highlight": [
            "May"
          ],
          "translations": {
            "zh-TW": "請問可以讓我看一下您的會員卡嗎？"
          }
        },
        {
          "en": "The new policy may take effect as early as next May.",
          "highlight": [
            "may"
          ],
          "translations": {
            "zh-TW": "新政策可能最早在明年五月生效。"
          }
        },
        {
          "en": "All employees, regardless of their Mays of joining, are eligible.",
          "highlight": [
            "Mays"
          ],
          "translations": {
            "zh-TW": "所有員工，無論是在哪個五月入職的，都符合資格。"
          }
        }
      ],
      "synonyms": [
        "might",
        "could",
        "perhaps"
      ],
      "antonyms": [
        "must",
        "will"
      ],
      "phrases": [
        "may I",
        "may not",
        "may be",
        "as of May"
      ]
    },
    {
      "id": "A2-180-004",
      "level": 180,
      "tier": "basic",
      "cefr": "A2",
      "toeic_score_min": 200,
      "word": "maybe",
      "pos": [
        "adverb"
      ],
      "conjugations": {},
      "domain": "general",
      "translations": [
        {
          "lang": "zh-TW",
          "lang_word": "maybe",
          "definition": "adv. 也許、大概、可能"
        }
      ],
      "examples": [
        {
          "en": "Maybe we should reschedule the conference call.",
          "highlight": [
            "Maybe"
          ],
          "translations": {
            "zh-TW": "也許我們應該重新安排這通電話會議。"
          }
        },
        {
          "en": "The client will maybe confirm the order by Friday.",
          "highlight": [
            "maybe"
          ],
          "translations": {
            "zh-TW": "客戶可能會在週五前確認訂單。"
          }
        },
        {
          "en": "Maybe yes, maybe no—either way we keep moving forward.",
          "highlight": [
            "maybe"
          ],
          "translations": {
            "zh-TW": "也許是，也許不是——無論如何我們都會繼續前進。"
          }
        }
      ],
      "synonyms": [
        "perhaps",
        "possibly",
        "potentially"
      ],
      "antonyms": [
        "certainly",
        "definitely",
        "surely"
      ],
      "phrases": [
        "maybe later",
        "maybe not",
        "maybe yes",
        "maybe so"
      ]
    },
    {
      "id": "A2-180-005",
      "level": 180,
      "tier": "basic",
      "cefr": "A2",
      "toeic_score_min": 200,
      "word": "mayor",
      "pos": [
        "noun"
      ],
      "conjugations": {
        "plural": "mayors",
        "present_3rd": "mayors",
        "past": "mayored",
        "past_participle": "mayored",
        "ing": "mayoring"
      },
      "domain": "general",
      "translations": [
        {
          "lang": "zh-TW",
          "lang_word": "mayor",
          "definition": "n. 市長、鎮長"
        }
      ],
      "examples": [
        {
          "en": "The mayor unveiled the new public transit plan this morning.",
          "highlight": [
            "mayor"
          ],
          "translations": {
            "zh-TW": "市長今天早上公布了新的公共運輸計畫。"
          }
        },
        {
          "en": "Several mayors from neighboring cities signed the trade agreement.",
          "highlight": [
            "mayors"
          ],
          "translations": {
            "zh-TW": "幾位鄰近城市的市長簽署了貿易協定。"
          }
        },
        {
          "en": "She mayored the small town for eight years before retiring.",
          "highlight": [
            "mayored"
          ],
          "translations": {
            "zh-TW": "她擔任了那座小鎮八年的鎮長才退休。"
          }
        }
      ],
      "synonyms": [
        "city head",
        "chief executive",
        "chief magistrate"
      ],
      "antonyms": [
        "constituency",
        "governor"
      ],
      "phrases": [
        "elected mayor",
        "new mayor",
        "mayor office",
        "lieutenant mayor"
      ]
    },
    {
      "id": "A2-180-006",
      "level": 180,
      "tier": "basic",
      "cefr": "A2",
      "toeic_score_min": 200,
      "word": "me",
      "pos": [
        "pronoun"
      ],
      "conjugations": {},
      "domain": "general",
      "translations": [
        {
          "lang": "zh-TW",
          "lang_word": "me",
          "definition": "pron. 我（受格）"
        }
      ],
      "examples": [
        {
          "en": "Please forward the invoice to me by end of day.",
          "highlight": [
            "me"
          ],
          "translations": {
            "zh-TW": "請在下班前把發票轉寄給我。"
          }
        },
        {
          "en": "HR told me the benefits package had been updated.",
          "highlight": [
            "me"
          ],
          "translations": {
            "zh-TW": "人資告訴我福利方案已經更新了。"
          }
        },
        {
          "en": "The vendor let me preview the prototype before the launch.",
          "highlight": [
            "me"
          ],
          "translations": {
            "zh-TW": "供應商讓我在發表會前預覽原型。"
          }
        }
      ],
      "synonyms": [
        "myself",
        "mine"
      ],
      "antonyms": [
        "you",
        "them",
        "others"
      ],
      "phrases": [
        "send me",
        "tell me",
        "give me",
        "help me"
      ]
    },
    {
      "id": "A2-180-007",
      "level": 180,
      "tier": "basic",
      "cefr": "A2",
      "toeic_score_min": 200,
      "word": "meal",
      "pos": [
        "noun"
      ],
      "conjugations": {
        "plural": "meals",
        "present_3rd": "meals",
        "past": "mealed",
        "past_participle": "mealed",
        "ing": "mealing"
      },
      "domain": "general",
      "translations": [
        {
          "lang": "zh-TW",
          "lang_word": "meal",
          "definition": "n. 一餐、膳食、餐點"
        }
      ],
      "examples": [
        {
          "en": "Lunch is the most important business meal of the day.",
          "highlight": [
            "meal"
          ],
          "translations": {
            "zh-TW": "商務午餐是一天中最重要的商務餐點。"
          }
        },
        {
          "en": "The hotel offers three meals daily, included in the rate.",
          "highlight": [
            "meals"
          ],
          "translations": {
            "zh-TW": "飯店每天提供三餐，已包含在房價中。"
          }
        },
        {
          "en": "Staff who mealed on-site saved time and expense reports.",
          "highlight": [
            "mealed"
          ],
          "translations": {
            "zh-TW": "在園區內用餐的員工省下了時間和報帳手續。"
          }
        }
      ],
      "synonyms": [
        "dish",
        "course",
        "feast"
      ],
      "antonyms": [
        "fast"
      ],
      "phrases": [
        "have a meal",
        "meal time",
        "business meal",
        "square meal"
      ]
    },
    {
      "id": "A2-180-008",
      "level": 180,
      "tier": "basic",
      "cefr": "A2",
      "toeic_score_min": 200,
      "word": "mean",
      "pos": [
        "verb",
        "noun",
        "adjective"
      ],
      "conjugations": {
        "plural": "means",
        "present_3rd": "means",
        "past": "meant",
        "past_participle": "meant",
        "ing": "meaning"
      },
      "domain": "general",
      "translations": [
        {
          "lang": "zh-TW",
          "lang_word": "mean",
          "definition": "v. 意指、意思是、具有重要意義  adj. 吝嗇的、刻薄的  n. 平均、中間"
        }
      ],
      "examples": [
        {
          "en": "What does this clause in the contract mean?",
          "highlight": [
            "mean"
          ],
          "translations": {
            "zh-TW": "合約中這個條款是什麼意思？"
          }
        },
        {
          "en": "The manager meant to send the report before leaving.",
          "highlight": [
            "meant"
          ],
          "translations": {
            "zh-TW": "經理原本打算在離開前把報告寄出。"
          }
        },
        {
          "en": "She is meaning to raise the issue at the next quarterly review.",
          "highlight": [
            "meaning"
          ],
          "translations": {
            "zh-TW": "她打算在下一次季度回顧會議上提出這個問題。"
          }
        }
      ],
      "synonyms": [
        "signify",
        "indicate",
        "imply"
      ],
      "antonyms": [
        "misunderstand",
        "confuse"
      ],
      "phrases": [
        "mean to",
        "what do you mean",
        "mean business",
        "got means"
      ]
    },
    {
      "id": "A2-180-009",
      "level": 180,
      "tier": "basic",
      "cefr": "A2",
      "toeic_score_min": 200,
      "word": "meaning",
      "pos": [
        "noun"
      ],
      "conjugations": {
        "plural": "meanings"
      },
      "domain": "general",
      "translations": [
        {
          "lang": "zh-TW",
          "lang_word": "meaning",
          "definition": "n. 意義、含義、意圖"
        }
      ],
      "examples": [
        {
          "en": "The legal jargon obscures the true meaning of the clause.",
          "highlight": [
            "meaning"
          ],
          "translations": {
            "zh-TW": "法律術語掩蓋了條款的真正含義。"
          }
        },
        {
          "en": "A single word can have several meanings in English.",
          "highlight": [
            "meanings"
          ],
          "translations": {
            "zh-TW": "一個英文單字可以有多種含義。"
          }
        },
        {
          "en": "The new CEO shared her vision about the company's meaning.",
          "highlight": [
            "meaning"
          ],
          "translations": {
            "zh-TW": "新任執行長分享了對於公司存在意義的願景。"
          }
        }
      ],
      "synonyms": [
        "definition",
        "sense",
        "significance"
      ],
      "antonyms": [
        "meaninglessness"
      ],
      "phrases": [
        "deep meaning",
        "exact meaning",
        "meaning of life",
        "lost its meaning"
      ]
    },
    {
      "id": "A2-180-010",
      "level": 180,
      "tier": "basic",
      "cefr": "A2",
      "toeic_score_min": 200,
      "word": "means",
      "pos": [
        "noun",
        "verb"
      ],
      "conjugations": {
        "plural": "means",
        "present_3rd": "means",
        "past": "meant",
        "past_participle": "meant",
        "ing": "meaning"
      },
      "domain": "general",
      "translations": [
        {
          "lang": "zh-TW",
          "lang_word": "means",
          "definition": "n. 方法、手段、資源、收入  v. mean 的第三人称單數"
        }
      ],
      "examples": [
        {
          "en": "The freight was shipped by railway, an economical means of transport.",
          "highlight": [
            "means"
          ],
          "translations": {
            "zh-TW": "貨物經由鐵路運送，這是一種經濟的運輸方式。"
          }
        },
        {
          "en": "She lives within her means and saves half her salary every month.",
          "highlight": [
            "means"
          ],
          "translations": {
            "zh-TW": "她量入為出，每個月將一半薪資存下來。"
          }
        },
        {
          "en": "The new billing system means clients pay less each quarter.",
          "highlight": [
            "means"
          ],
          "translations": {
            "zh-TW": "新的帳單系統讓客戶每季支付的費用更低。"
          }
        }
      ],
      "synonyms": [
        "method",
        "way",
        "resources"
      ],
      "antonyms": [
        "end"
      ],
      "phrases": [
        "means to an end",
        "by all means",
        "by means of",
        "within one's means"
      ]
    }
  ]
}