{
  "level": 701,
  "tier": "advanced",
  "cefr": "C2",
  "words": [
    {
      "id": "C2-701-001",
      "level": 701,
      "tier": "advanced",
      "cefr": "C2",
      "toeic_score_min": 920,
      "word": "quebec",
      "phonetic": "",
      "pos": [
        "noun"
      ],
      "conjugations": {
        "plural": "quebecs"
      },
      "domain": "general",
      "translations": [
        {
          "lang": "zh-TW",
          "lang_word": "quebec",
          "definition": "n. 魁北克（加拿大港市省名）"
        }
      ],
      "examples": [],
      "synonyms": [],
      "antonyms": [],
      "phrases": []
    },
    {
      "id": "C2-701-002",
      "level": 701,
      "tier": "advanced",
      "cefr": "C2",
      "toeic_score_min": 920,
      "word": "dennis",
      "phonetic": "",
      "pos": [
        "noun"
      ],
      "conjugations": {
        "plural": "dennises"
      },
      "domain": "general",
      "translations": [
        {
          "lang": "zh-TW",
          "lang_word": "dennis",
          "definition": "n. 丹尼斯（男子名）"
        }
      ],
      "examples": [],
      "synonyms": [],
      "antonyms": [],
      "phrases": []
    },
    {
      "id": "C2-701-003",
      "level": 701,
      "tier": "advanced",
      "cefr": "C2",
      "toeic_score_min": 920,
      "word": "mars",
      "phonetic": "",
      "pos": [
        "noun"
      ],
      "conjugations": {
        "plural": "marses"
      },
      "domain": "general",
      "translations": [
        {
          "lang": "zh-TW",
          "lang_word": "mars",
          "definition": "n. 火星, 战神, [醫] 鐵"
        }
      ],
      "examples": [],
      "synonyms": [],
      "antonyms": [],
      "phrases": []
    },
    {
      "id": "C2-701-004",
      "level": 701,
      "tier": "advanced",
      "cefr": "C2",
      "toeic_score_min": 920,
      "word": "francis",
      "phonetic": "",
      "pos": [
        "noun"
      ],
      "conjugations": {
        "plural": "francises"
      },
      "domain": "general",
      "translations": [
        {
          "lang": "zh-TW",
          "lang_word": "francis",
          "definition": "n. 弗朗西斯（男子名, 义為自由之人）"
        }
      ],
      "examples": [],
      "synonyms": [],
      "antonyms": [],
      "phrases": []
    },
    {
      "id": "C2-701-005",
      "level": 701,
      "tier": "advanced",
      "cefr": "C2",
      "toeic_score_min": 920,
      "word": "tvs",
      "phonetic": "",
      "pos": [
        "noun"
      ],
      "conjugations": {
        "plural": "tvses"
      },
      "domain": "general",
      "translations": [
        {
          "lang": "zh-TW",
          "lang_word": "tvs",
          "definition": "abbr. 瞬变電压抑制二極管（Transient Voltage Suppressors）；電視觀察系统（Television Viewing Systems）"
        }
      ],
      "examples": [],
      "synonyms": [],
      "antonyms": [],
      "phrases": []
    },
    {
      "id": "C2-701-006",
      "level": 701,
      "tier": "advanced",
      "cefr": "C2",
      "toeic_score_min": 920,
      "word": "sized",
      "phonetic": "",
      "pos": [
        "noun"
      ],
      "conjugations": {
        "plural": "sizeds"
      },
      "domain": "general",
      "translations": [
        {
          "lang": "zh-TW",
          "lang_word": "sized",
          "definition": "a. 依大小排列的, 依大小調整的, 型號的, ...尺码的"
        }
      ],
      "examples": [],
      "synonyms": [],
      "antonyms": [],
      "phrases": []
    },
    {
      "id": "C2-701-007",
      "level": 701,
      "tier": "advanced",
      "cefr": "C2",
      "toeic_score_min": 920,
      "word": "manga",
      "phonetic": "",
      "pos": [
        "noun"
      ],
      "conjugations": {
        "plural": "mangas"
      },
      "domain": "general",
      "translations": [
        {
          "lang": "zh-TW",
          "lang_word": "manga",
          "definition": "n. 日本漫画"
        }
      ],
      "examples": [],
      "synonyms": [],
      "antonyms": [],
      "phrases": []
    },
    {
      "id": "C2-701-008",
      "level": 701,
      "tier": "advanced",
      "cefr": "C2",
      "toeic_score_min": 920,
      "word": "noticed",
      "phonetic": "",
      "pos": [
        "noun"
      ],
      "conjugations": {
        "plural": "noticeds"
      },
      "domain": "general",
      "translations": [
        {
          "lang": "zh-TW",
          "lang_word": "noticed",
          "definition": "v. 注意（ notice的過去式和過去分词 ）; 觉察"
        }
      ],
      "examples": [],
      "synonyms": [],
      "antonyms": [],
      "phrases": []
    },
    {
      "id": "C2-701-009",
      "level": 701,
      "tier": "advanced",
      "cefr": "C2",
      "toeic_score_min": 920,
      "word": "socket",
      "phonetic": "",
      "pos": [
        "noun"
      ],
      "conjugations": {
        "plural": "sockets"
      },
      "domain": "general",
      "translations": [
        {
          "lang": "zh-TW",
          "lang_word": "socket",
          "definition": "n. 窝, 穴, 插座, 眼窝, vt. 插进插座, [計] 套接字"
        }
      ],
      "examples": [],
      "synonyms": [],
      "antonyms": [],
      "phrases": []
    },
    {
      "id": "C2-701-010",
      "level": 701,
      "tier": "advanced",
      "cefr": "C2",
      "toeic_score_min": 920,
      "word": "mhz",
      "phonetic": "",
      "pos": [
        "noun"
      ],
      "conjugations": {
        "plural": "mhzs"
      },
      "domain": "general",
      "translations": [
        {
          "lang": "zh-TW",
          "lang_word": "mhz",
          "definition": "[計] 兆赫兹"
        }
      ],
      "examples": [],
      "synonyms": [],
      "antonyms": [],
      "phrases": []
    }
  ],
  "_skeleton": true
}