{
  "level": 778,
  "tier": "advanced",
  "cefr": "C2",
  "words": [
    {
      "id": "C2-778-001",
      "level": 778,
      "tier": "advanced",
      "cefr": "C2",
      "toeic_score_min": 920,
      "word": "fisheries",
      "phonetic": "",
      "pos": [
        "noun"
      ],
      "conjugations": {
        "plural": "fisherieses"
      },
      "domain": "general",
      "translations": [
        {
          "lang": "zh-TW",
          "lang_word": "fisheries",
          "definition": "n. 渔場( fishery的名词复数 ); 渔業; 养鱼場"
        }
      ],
      "examples": [],
      "synonyms": [],
      "antonyms": [],
      "phrases": []
    },
    {
      "id": "C2-778-002",
      "level": 778,
      "tier": "advanced",
      "cefr": "C2",
      "toeic_score_min": 920,
      "word": "exceptions",
      "phonetic": "",
      "pos": [
        "noun"
      ],
      "conjugations": {
        "plural": "exceptionses"
      },
      "domain": "general",
      "translations": [
        {
          "lang": "zh-TW",
          "lang_word": "exceptions",
          "definition": "n. 免责条款（exception的复数形式）"
        }
      ],
      "examples": [],
      "synonyms": [],
      "antonyms": [],
      "phrases": []
    },
    {
      "id": "C2-778-003",
      "level": 778,
      "tier": "advanced",
      "cefr": "C2",
      "toeic_score_min": 920,
      "word": "reactions",
      "phonetic": "",
      "pos": [
        "noun"
      ],
      "conjugations": {
        "plural": "reactionses"
      },
      "domain": "general",
      "translations": [
        {
          "lang": "zh-TW",
          "lang_word": "reactions",
          "definition": "n. 反應（reaction的复数）"
        }
      ],
      "examples": [],
      "synonyms": [],
      "antonyms": [],
      "phrases": []
    },
    {
      "id": "C2-778-004",
      "level": 778,
      "tier": "advanced",
      "cefr": "C2",
      "toeic_score_min": 920,
      "word": "leasing",
      "phonetic": "",
      "pos": [
        "noun"
      ],
      "conjugations": {
        "plural": "leasings"
      },
      "domain": "general",
      "translations": [
        {
          "lang": "zh-TW",
          "lang_word": "leasing",
          "definition": "n. 說谎"
        }
      ],
      "examples": [],
      "synonyms": [],
      "antonyms": [],
      "phrases": []
    },
    {
      "id": "C2-778-005",
      "level": 778,
      "tier": "advanced",
      "cefr": "C2",
      "toeic_score_min": 920,
      "word": "lauren",
      "phonetic": "",
      "pos": [
        "noun"
      ],
      "conjugations": {
        "plural": "laurens"
      },
      "domain": "general",
      "translations": [
        {
          "lang": "zh-TW",
          "lang_word": "lauren",
          "definition": "n. 劳伦（姓氏）"
        }
      ],
      "examples": [],
      "synonyms": [],
      "antonyms": [],
      "phrases": []
    },
    {
      "id": "C2-778-006",
      "level": 778,
      "tier": "advanced",
      "cefr": "C2",
      "toeic_score_min": 920,
      "word": "beliefs",
      "phonetic": "",
      "pos": [
        "noun"
      ],
      "conjugations": {
        "plural": "beliefses"
      },
      "domain": "general",
      "translations": [
        {
          "lang": "zh-TW",
          "lang_word": "beliefs",
          "definition": "n. 信仰；信?（belief的复数）"
        }
      ],
      "examples": [],
      "synonyms": [],
      "antonyms": [],
      "phrases": []
    },
    {
      "id": "C2-778-007",
      "level": 778,
      "tier": "advanced",
      "cefr": "C2",
      "toeic_score_min": 920,
      "word": "macromedia",
      "phonetic": "",
      "pos": [
        "noun"
      ],
      "conjugations": {
        "plural": "macromedias"
      },
      "domain": "general",
      "translations": [
        {
          "lang": "zh-TW",
          "lang_word": "macromedia",
          "definition": "全球最大的网络多媒体软件公司; 旗下的软件包括Macromedia Flash; Macromedia Dreamweaver; Macromedia Fireworks"
        }
      ],
      "examples": [],
      "synonyms": [],
      "antonyms": [],
      "phrases": []
    },
    {
      "id": "C2-778-008",
      "level": 778,
      "tier": "advanced",
      "cefr": "C2",
      "toeic_score_min": 920,
      "word": "ashley",
      "phonetic": "",
      "pos": [
        "noun"
      ],
      "conjugations": {
        "plural": "ashleies"
      },
      "domain": "general",
      "translations": [
        {
          "lang": "zh-TW",
          "lang_word": "ashley",
          "definition": "n. 艾希莉（人名）"
        }
      ],
      "examples": [],
      "synonyms": [],
      "antonyms": [],
      "phrases": []
    },
    {
      "id": "C2-778-009",
      "level": 778,
      "tier": "advanced",
      "cefr": "C2",
      "toeic_score_min": 920,
      "word": "scroll",
      "phonetic": "",
      "pos": [
        "noun"
      ],
      "conjugations": {
        "plural": "scrolls"
      },
      "domain": "general",
      "translations": [
        {
          "lang": "zh-TW",
          "lang_word": "scroll",
          "definition": "n. 卷轴, 画卷, 名册, 条幅, 滚動, v. (使)成卷形, [计] 滚動"
        }
      ],
      "examples": [],
      "synonyms": [],
      "antonyms": [],
      "phrases": []
    },
    {
      "id": "C2-778-010",
      "level": 778,
      "tier": "advanced",
      "cefr": "C2",
      "toeic_score_min": 920,
      "word": "divisions",
      "phonetic": "",
      "pos": [
        "noun"
      ],
      "conjugations": {
        "plural": "divisionses"
      },
      "domain": "general",
      "translations": [
        {
          "lang": "zh-TW",
          "lang_word": "divisions",
          "definition": "n. 分开( division的复数形式 ); 分界線; 分歧; 分離"
        }
      ],
      "examples": [],
      "synonyms": [],
      "antonyms": [],
      "phrases": []
    }
  ],
  "_skeleton": true
}