{
  "level": 357,
  "tier": "intermediate",
  "cefr": "B1",
  "words": [
    {
      "id": "B1-357-001",
      "level": 357,
      "tier": "intermediate",
      "cefr": "B1",
      "toeic_score_min": 650,
      "word": "founder",
      "phonetic": "",
      "pos": [
        "noun"
      ],
      "conjugations": {
        "plural": "founders"
      },
      "domain": "general",
      "translations": [
        {
          "lang": "zh-TW",
          "lang_word": "founder",
          "definition": "n. 創立者, 建立者, vt. 使沉没, 使摔倒, 弄跛, 浸水, 破坏, vi. 沉没, 摔到, 变跛, 倒塌, 失败"
        }
      ],
      "examples": [],
      "synonyms": [],
      "antonyms": [],
      "phrases": []
    },
    {
      "id": "B1-357-002",
      "level": 357,
      "tier": "intermediate",
      "cefr": "B1",
      "toeic_score_min": 650,
      "word": "fundraise",
      "phonetic": "",
      "pos": [
        "noun"
      ],
      "conjugations": {
        "plural": "fundraises"
      },
      "domain": "general",
      "translations": [
        {
          "lang": "zh-TW",
          "lang_word": "fundraise",
          "definition": "n. 募捐"
        }
      ],
      "examples": [],
      "synonyms": [],
      "antonyms": [],
      "phrases": []
    },
    {
      "id": "B1-357-003",
      "level": 357,
      "tier": "intermediate",
      "cefr": "B1",
      "toeic_score_min": 650,
      "word": "graphics",
      "phonetic": "",
      "pos": [
        "noun"
      ],
      "conjugations": {
        "plural": "graphicses"
      },
      "domain": "general",
      "translations": [
        {
          "lang": "zh-TW",
          "lang_word": "graphics",
          "definition": "n. 制圖法, 制圖學, 圖解算法, 圖形顯示, [計] 圖形; DOS外部命令:打印圖形方式下的屏幕內容"
        }
      ],
      "examples": [],
      "synonyms": [],
      "antonyms": [],
      "phrases": []
    },
    {
      "id": "B1-357-004",
      "level": 357,
      "tier": "intermediate",
      "cefr": "B1",
      "toeic_score_min": 650,
      "word": "handy",
      "phonetic": "",
      "pos": [
        "noun"
      ],
      "conjugations": {
        "plural": "handies"
      },
      "domain": "general",
      "translations": [
        {
          "lang": "zh-TW",
          "lang_word": "handy",
          "definition": "a. 便利的, 敏捷的, 容易取得的, [化] 便于使用的; 易操作的"
        }
      ],
      "examples": [],
      "synonyms": [],
      "antonyms": [],
      "phrases": []
    },
    {
      "id": "B1-357-005",
      "level": 357,
      "tier": "intermediate",
      "cefr": "B1",
      "toeic_score_min": 650,
      "word": "hazardous",
      "phonetic": "",
      "pos": [
        "noun"
      ],
      "conjugations": {
        "plural": "hazardouses"
      },
      "domain": "general",
      "translations": [
        {
          "lang": "zh-TW",
          "lang_word": "hazardous",
          "definition": "a. 危险的, 冒险的, 碰運气的, [法] 危险的, 冒险的, 碰運气的"
        }
      ],
      "examples": [],
      "synonyms": [],
      "antonyms": [],
      "phrases": []
    },
    {
      "id": "B1-357-006",
      "level": 357,
      "tier": "intermediate",
      "cefr": "B1",
      "toeic_score_min": 650,
      "word": "healthcare",
      "phonetic": "",
      "pos": [
        "noun"
      ],
      "conjugations": {
        "plural": "healthcares"
      },
      "domain": "general",
      "translations": [
        {
          "lang": "zh-TW",
          "lang_word": "healthcare",
          "definition": "n. 醫疗保健；卫生保健；健康護理, 健康服務"
        }
      ],
      "examples": [],
      "synonyms": [],
      "antonyms": [],
      "phrases": []
    },
    {
      "id": "B1-357-007",
      "level": 357,
      "tier": "intermediate",
      "cefr": "B1",
      "toeic_score_min": 650,
      "word": "humidity",
      "phonetic": "",
      "pos": [
        "noun"
      ],
      "conjugations": {
        "plural": "humidities"
      },
      "domain": "general",
      "translations": [
        {
          "lang": "zh-TW",
          "lang_word": "humidity",
          "definition": "n. 湿气, 潮湿, 湿度, [計] 湿度"
        }
      ],
      "examples": [],
      "synonyms": [],
      "antonyms": [],
      "phrases": []
    },
    {
      "id": "B1-357-008",
      "level": 357,
      "tier": "intermediate",
      "cefr": "B1",
      "toeic_score_min": 650,
      "word": "influential",
      "phonetic": "",
      "pos": [
        "noun"
      ],
      "conjugations": {
        "plural": "influentials"
      },
      "domain": "general",
      "translations": [
        {
          "lang": "zh-TW",
          "lang_word": "influential",
          "definition": "a. 有影响的, 有势力的"
        }
      ],
      "examples": [],
      "synonyms": [],
      "antonyms": [],
      "phrases": []
    },
    {
      "id": "B1-357-009",
      "level": 357,
      "tier": "intermediate",
      "cefr": "B1",
      "toeic_score_min": 650,
      "word": "nationwide",
      "phonetic": "",
      "pos": [
        "noun"
      ],
      "conjugations": {
        "plural": "nationwides"
      },
      "domain": "general",
      "translations": [
        {
          "lang": "zh-TW",
          "lang_word": "nationwide",
          "definition": "a. 全國性的, [法] 全國的, 全國范圍的"
        }
      ],
      "examples": [],
      "synonyms": [],
      "antonyms": [],
      "phrases": []
    },
    {
      "id": "B1-357-010",
      "level": 357,
      "tier": "intermediate",
      "cefr": "B1",
      "toeic_score_min": 650,
      "word": "pad",
      "phonetic": "",
      "pos": [
        "noun"
      ],
      "conjugations": {
        "plural": "pads"
      },
      "domain": "general",
      "translations": [
        {
          "lang": "zh-TW",
          "lang_word": "pad",
          "definition": "n. 填补, 衬垫, 印色盒, 路, vt. 填补, 走, 夸大, vi. 步行, [計] 焊接點; 包裝配/拆卸"
        }
      ],
      "examples": [],
      "synonyms": [],
      "antonyms": [],
      "phrases": []
    }
  ],
  "_skeleton": true
}