{
  "level": 557,
  "tier": "intermediate",
  "cefr": "B2",
  "words": [
    {
      "id": "B2-557-001",
      "level": 557,
      "tier": "intermediate",
      "cefr": "B2",
      "toeic_score_min": 750,
      "word": "leaders",
      "phonetic": "",
      "pos": [
        "noun"
      ],
      "conjugations": {
        "plural": "leaderses"
      },
      "domain": "general",
      "translations": [
        {
          "lang": "zh-TW",
          "lang_word": "leaders",
          "definition": "n. 指挥；引線；前導字符；領袖（leader的复数）"
        }
      ],
      "examples": [],
      "synonyms": [],
      "antonyms": [],
      "phrases": []
    },
    {
      "id": "B2-557-002",
      "level": 557,
      "tier": "intermediate",
      "cefr": "B2",
      "toeic_score_min": 750,
      "word": "posters",
      "phonetic": "",
      "pos": [
        "noun"
      ],
      "conjugations": {
        "plural": "posterses"
      },
      "domain": "general",
      "translations": [
        {
          "lang": "zh-TW",
          "lang_word": "posters",
          "definition": "n. 招贴, 海報( poster的复数形式 ); 印成的大幅画"
        }
      ],
      "examples": [],
      "synonyms": [],
      "antonyms": [],
      "phrases": []
    },
    {
      "id": "B2-557-003",
      "level": 557,
      "tier": "intermediate",
      "cefr": "B2",
      "toeic_score_min": 750,
      "word": "institutions",
      "phonetic": "",
      "pos": [
        "noun"
      ],
      "conjugations": {
        "plural": "institutionses"
      },
      "domain": "general",
      "translations": [
        {
          "lang": "zh-TW",
          "lang_word": "institutions",
          "definition": "n. 体系"
        }
      ],
      "examples": [],
      "synonyms": [],
      "antonyms": [],
      "phrases": []
    },
    {
      "id": "B2-557-004",
      "level": 557,
      "tier": "intermediate",
      "cefr": "B2",
      "toeic_score_min": 750,
      "word": "headlines",
      "phonetic": "",
      "pos": [
        "noun"
      ],
      "conjugations": {
        "plural": "headlineses"
      },
      "domain": "general",
      "translations": [
        {
          "lang": "zh-TW",
          "lang_word": "headlines",
          "definition": "n. 大字标题( headline的名词复数 ); 新聞提要"
        }
      ],
      "examples": [],
      "synonyms": [],
      "antonyms": [],
      "phrases": []
    },
    {
      "id": "B2-557-005",
      "level": 557,
      "tier": "intermediate",
      "cefr": "B2",
      "toeic_score_min": 750,
      "word": "compared",
      "phonetic": "",
      "pos": [
        "noun"
      ],
      "conjugations": {
        "plural": "compareds"
      },
      "domain": "general",
      "translations": [
        {
          "lang": "zh-TW",
          "lang_word": "compared",
          "definition": "a. 比较的, 對照的（compare的過去式和過去分词）"
        }
      ],
      "examples": [],
      "synonyms": [],
      "antonyms": [],
      "phrases": []
    },
    {
      "id": "B2-557-006",
      "level": 557,
      "tier": "intermediate",
      "cefr": "B2",
      "toeic_score_min": 750,
      "word": "wholesale",
      "phonetic": "",
      "pos": [
        "noun"
      ],
      "conjugations": {
        "plural": "wholesales"
      },
      "domain": "general",
      "translations": [
        {
          "lang": "zh-TW",
          "lang_word": "wholesale",
          "definition": "n. 批發, a. 批發的, 大规模的, adv. 大规模, 照批發方式, vi. 經营批發業, 批發, vt. 批發"
        }
      ],
      "examples": [],
      "synonyms": [],
      "antonyms": [],
      "phrases": []
    },
    {
      "id": "B2-557-007",
      "level": 557,
      "tier": "intermediate",
      "cefr": "B2",
      "toeic_score_min": 750,
      "word": "russia",
      "phonetic": "",
      "pos": [
        "noun"
      ],
      "conjugations": {
        "plural": "russias"
      },
      "domain": "general",
      "translations": [
        {
          "lang": "zh-TW",
          "lang_word": "russia",
          "definition": "n. 俄國, 俄罗斯, [法] 俄罗斯, 苏联"
        }
      ],
      "examples": [],
      "synonyms": [],
      "antonyms": [],
      "phrases": []
    },
    {
      "id": "B2-557-008",
      "level": 557,
      "tier": "intermediate",
      "cefr": "B2",
      "toeic_score_min": 750,
      "word": "gone",
      "phonetic": "",
      "pos": [
        "noun"
      ],
      "conjugations": {
        "plural": "gones"
      },
      "domain": "general",
      "translations": [
        {
          "lang": "zh-TW",
          "lang_word": "gone",
          "definition": "a. 離去的, 死去的, 用完的, go的過去分词"
        }
      ],
      "examples": [],
      "synonyms": [],
      "antonyms": [],
      "phrases": []
    },
    {
      "id": "B2-557-009",
      "level": 557,
      "tier": "intermediate",
      "cefr": "B2",
      "toeic_score_min": 750,
      "word": "codes",
      "phonetic": "",
      "pos": [
        "noun"
      ],
      "conjugations": {
        "plural": "codeses"
      },
      "domain": "general",
      "translations": [
        {
          "lang": "zh-TW",
          "lang_word": "codes",
          "definition": "n. 编码, 代码；规范；准则（code的复数）"
        }
      ],
      "examples": [],
      "synonyms": [],
      "antonyms": [],
      "phrases": []
    },
    {
      "id": "B2-557-010",
      "level": 557,
      "tier": "intermediate",
      "cefr": "B2",
      "toeic_score_min": 750,
      "word": "kinds",
      "phonetic": "",
      "pos": [
        "noun"
      ],
      "conjugations": {
        "plural": "kindses"
      },
      "domain": "general",
      "translations": [
        {
          "lang": "zh-TW",
          "lang_word": "kinds",
          "definition": "n. 種类（kind的复数形式）"
        }
      ],
      "examples": [],
      "synonyms": [],
      "antonyms": [],
      "phrases": []
    }
  ],
  "_skeleton": true
}